kioku/__init__.py
kioku/cache.py
kioku-0.1.0.dist-info/LICENSE
kioku-0.1.0.dist-info/WHEEL
kioku-0.1.0.dist-info/METADATA
kioku-0.1.0.dist-info/RECORD
