Metadata-Version: 2.1
Name: kioku
Version: 0.1.0
Summary: Python package project template.
Home-page: https://github.com/takelushi/kioku
License: MIT
Author: Takeru Saito
Author-email: takelushi@gmail.com
Requires-Python: >=3.7,<4.0
Classifier: License :: OSI Approved :: MIT License
Classifier: Programming Language :: Python :: 3
Classifier: Programming Language :: Python :: 3.10
Classifier: Programming Language :: Python :: 3.7
Classifier: Programming Language :: Python :: 3.8
Classifier: Programming Language :: Python :: 3.9
Project-URL: Repository, https://github.com/takelushi/kioku
Project-URL: issues, https://github.com/takelushi/kioku/issues
